evo_shell/__init__.py
evo_shell/loop.py
evo_shell/main.py
evo_shell/test.py
evo_shell/connections/__init__.py
evo_shell/connections/connections.py
evo_shell/connections/redis.py
evo_shell/core/__init__.py
evo_shell/core/config.py
evo_shell/core/core_consumer.py
evo_shell/core/process_controller.py
evo_shell/core/generator/__init__.py
evo_shell/core/generator/message_generator.py
evo_shell/core/rabbitmq/__init__.py
evo_shell/core/rabbitmq/rabbitmq_consumer.py
evo_shell/core/rabbitmq/rabbitmq_producer.py
evo_shell/core/rabbitmq/rabbitmq_utils.py
evo_shell/log_service/__init__.py
evo_shell/log_service/device_command_handler.py
evo_shell/log_service/logcollector_controller.py
evo_shell/log_service/adb_log/__init__.py
evo_shell/log_service/adb_log/log_manager.py
evo_shell/log_service/adb_log/parse.py
evo_shell/util/__init__.py
evo_shell/util/common.py
tests/__init__.py
evo_shell-0.0.13.dist-info/METADATA
evo_shell-0.0.13.dist-info/WHEEL
evo_shell-0.0.13.dist-info/top_level.txt
evo_shell-0.0.13.dist-info/RECORD
